em73xx
