Metadata-Version: 1.1
Name: em73xx
Version: 0.11
Summary: python wrapper for the em73xx series of 4G modems present in recent Lenovo Thinkpads
Home-page: https://github.com/smcl/py-em73xx
Author: Sean McLemon
Author-email: sean.mclemon@gmail.com
License: UNKNOWN
Download-URL: https://github.com/smcl/py-em73xx/tarball/0.11
Keywords: thinkpad,em7345,em73xx
Platform: UNKNOWN
